distancematrix/__init__.py
distancematrix/calculator.py
distancematrix/insights.py
distancematrix/interrupt_util.py
distancematrix/math_tricks.py
distancematrix/ostinato.py
distancematrix/ringbuffer.py
distancematrix/util.py
distancematrix/valmod.py
distancematrix/consumer/__init__.py
distancematrix/consumer/abstract_consumer.py
distancematrix/consumer/contextmanager.py
distancematrix/consumer/contextual_matrix_profile.py
distancematrix/consumer/distance_matrix.py
distancematrix/consumer/matrix_profile_lr.py
distancematrix/consumer/multidimensional_matrix_profile_lr.py
distancematrix/consumer/radius_profile.py
distancematrix/consumer/threshold_counter.py
distancematrix/generator/__init__.py
distancematrix/generator/abstract_generator.py
distancematrix/generator/euclidean.py
distancematrix/generator/filter_generator.py
distancematrix/generator/znorm_euclidean.py
seriesdistancematrix-0.3.1.dist-info/LICENSE.txt
seriesdistancematrix-0.3.1.dist-info/METADATA
seriesdistancematrix-0.3.1.dist-info/WHEEL
seriesdistancematrix-0.3.1.dist-info/top_level.txt
seriesdistancematrix-0.3.1.dist-info/RECORD
