Metadata-Version: 2.1
Name: seriesdistancematrix
Version: 0.3.1
Summary: Flexible time series analysis libraryimplementing Matrix Profile related functionality.
Home-page: https://github.com/predict-idlab/seriesdistancematrix/
Author: Dieter De Paepe
Author-email: dieter.depaepe@gmail.com
License: MIT
Project-URL: Documentation, https://predict-idlab.github.io/seriesdistancematrix/
Project-URL: Source, https://github.com/predict-idlab/seriesdistancematrix/
Keywords: time series,matrix profile,contextual matrix profile,radius profile,series distance matrix,motif,discord
Platform: UNKNOWN
Classifier: License :: OSI Approved :: MIT License
Classifier: Intended Audience :: Science/Research
Classifier: Intended Audience :: Developers
Classifier: Topic :: Software Development
Classifier: Topic :: Scientific/Engineering
Classifier: Programming Language :: Python
Classifier: Programming Language :: Python :: 3
Classifier: Operating System :: OS Independent
Requires-Dist: numpy
Requires-Dist: scipy
Requires-Dist: pandas
